fauasg/__init__.py
fauasg-0.1.0.dist-info/LICENSE
fauasg-0.1.0.dist-info/METADATA
fauasg-0.1.0.dist-info/WHEEL
fauasg-0.1.0.dist-info/top_level.txt
fauasg-0.1.0.dist-info/RECORD
