Metadata-Version: 2.1
Name: fauasg
Version: 0.1.0
Summary: A set of tools developed by the Animal Speech Group at FAU
Home-page: https://github.com/alexanderbarnhill/fauasg
Author: Alexander Barnhill
Author-email: alexander.barnhill@fau.de
License: MIT
License-File: LICENSE
Requires-Dist: torch
Requires-Dist: numpy
Requires-Dist: matplotlib
Requires-Dist: scikit-learn
Requires-Dist: lightning
Requires-Dist: scikit-image
Requires-Dist: omegaconf
Requires-Dist: opencv-python
Requires-Dist: wandb
